pyepd/DisplayPanelController.py
pyepd/ImageHandler.py
pyepd/__init__.py
pyepd-0.1.data/scripts/img2epd
pyepd-0.1.dist-info/DESCRIPTION.rst
pyepd-0.1.dist-info/METADATA
pyepd-0.1.dist-info/RECORD
pyepd-0.1.dist-info/WHEEL
pyepd-0.1.dist-info/metadata.json
pyepd-0.1.dist-info/top_level.txt
